google_crc32c/__config__.py
google_crc32c/__init__.py
google_crc32c/_checksum.py
google_crc32c/_crc32c.pypy311-pp73-x86_64-linux-gnu.so
google_crc32c/cext.py
google_crc32c/py.typed
google_crc32c/python.py
google_crc32c.libs/libcrc32c-7ebc40c5.so.1.1.0
google_crc32c-1.7.0.dist-info/LICENSE
google_crc32c-1.7.0.dist-info/METADATA
google_crc32c-1.7.0.dist-info/WHEEL
google_crc32c-1.7.0.dist-info/top_level.txt
google_crc32c-1.7.0.dist-info/zip-safe
google_crc32c-1.7.0.dist-info/RECORD
